{"id":38,"name":"AB Pic","stars":[{"name":"AB Pic","type":"star","distance":47.3,"spec":"K","temp":4875,"radius":0.98,"lum":0.480532,"minhz":0.546,"maxhz":1.327,"planets":1,"texture":""}],"satellites":[{"name":"AB Pic b","type":"planet","masse":4292.19,"distance":47.3,"temp":12.8,"radius":11.37,"semiMajorAxis":41139414442.5,"eccentricity":0,"inclination":0,"siderealOrbitPeriod":0,"omega":0,"confirmed":1,"habitable":0,"habitableMoon":0,"esi":"0.06","method":"Imaging","year":"2005.00","tempClass":"cold","class":"jovian","color":null,"texture":"cold-jovian.jpg"}]}