{"id":81,"name":"CoRoT-21","stars":[{"name":"CoRoT-21","type":"star","distance":0,"spec":"F","temp":6200,"radius":1.95,"lum":5.015286,"minhz":1.638,"maxhz":3.822,"planets":1,"texture":""}],"satellites":[{"name":"CoRoT-21 b","type":"planet","masse":718.54,"distance":0,"temp":1867,"radius":14.56,"semiMajorAxis":6238231.20819,"eccentricity":0,"inclination":86.8,"siderealOrbitPeriod":2.72,"omega":0,"confirmed":1,"habitable":0,"habitableMoon":0,"esi":"0.06","method":"Transit","year":"2011.00","tempClass":"hot","class":"jovian","color":null,"texture":"hot-jovian.jpg"}]}