{"id":1019,"name":"Kepler-167","stars":[{"name":"Kepler-167","type":"star","distance":0,"spec":"K","temp":4796,"radius":0.7,"lum":0.232596,"minhz":0.381,"maxhz":0.93,"planets":2,"texture":""}],"satellites":[{"name":"Kepler-167 b","type":"planet","masse":3.05,"distance":0,"temp":807.6,"radius":1.44,"semiMajorAxis":7180697.7936,"eccentricity":0,"inclination":0,"siderealOrbitPeriod":4.39,"omega":0,"confirmed":1,"habitable":0,"habitableMoon":0,"esi":"0.29","method":"Transit","year":"2014.00","tempClass":"hot","class":"terran","color":null,"texture":"hot-terran.jpg"},{"name":"Kepler-167 c","type":"planet","masse":2.51,"distance":0,"temp":678.5,"radius":1.37,"semiMajorAxis":10172655.2076,"eccentricity":0,"inclination":0,"siderealOrbitPeriod":7.41,"omega":0,"confirmed":1,"habitable":0,"habitableMoon":0,"esi":"0.31","method":"Transit","year":"2014.00","tempClass":"hot","class":"terran","color":null,"texture":"hot-terran.jpg"}]}