{"id":1445,"name":"Kepler-336","stars":[{"name":"Kepler-336","type":"star","distance":0,"spec":"G","temp":5867,"radius":1.3,"lum":1.796557,"minhz":1,"maxhz":2.352,"planets":3,"texture":""}],"satellites":[{"name":"Kepler-336 b","type":"planet","masse":0.92,"distance":0,"temp":1623.7,"radius":1.02,"semiMajorAxis":4936729.7331,"eccentricity":0,"inclination":0,"siderealOrbitPeriod":2.02,"omega":0,"confirmed":1,"habitable":0,"habitableMoon":0,"esi":"0.29","method":"Transit","year":"2014.00","tempClass":"hot","class":"terran","color":null,"texture":"hot-terran.jpg"},{"name":"Kepler-336 c","type":"planet","masse":12.42,"distance":0,"temp":972.4,"radius":2.09,"semiMajorAxis":13763004.1044,"eccentricity":0,"inclination":0,"siderealOrbitPeriod":9.6,"omega":0,"confirmed":1,"habitable":0,"habitableMoon":0,"esi":"0.26","method":"Transit","year":"2014.00","tempClass":"hot","class":"superterran","color":null,"texture":"hot-superterran.jpg"},{"name":"Kepler-336 d","type":"planet","masse":20.8,"distance":0,"temp":751.6,"radius":2.36,"semiMajorAxis":23038072.0878,"eccentricity":0,"inclination":0,"siderealOrbitPeriod":20.68,"omega":0,"confirmed":1,"habitable":0,"habitableMoon":0,"esi":"0.25","method":"Transit","year":"2014.00","tempClass":"hot","class":"superterran","color":null,"texture":"hot-superterran.jpg"}]}