{"id":1711,"name":"OGLE-TR-10","stars":[{"name":"OGLE-TR-10","type":"star","distance":1500,"spec":"G","temp":6075,"radius":1.16,"lum":1.644337,"minhz":0.945,"maxhz":2.211,"planets":1,"texture":""}],"satellites":[{"name":"OGLE-TR-10 b","type":"planet","masse":216.2,"distance":1500,"temp":1414.1,"radius":19.26,"semiMajorAxis":6223271.42112,"eccentricity":0,"inclination":84.5,"siderealOrbitPeriod":3.1,"omega":0,"confirmed":1,"habitable":0,"habitableMoon":0,"esi":"0.05","method":"Transit","year":"2004.00","tempClass":"hot","class":"jovian","color":null,"texture":"hot-jovian.jpg"}]}