{"id":1724,"name":"OY Car","stars":[{"name":"OY Car","type":"star","distance":0,"spec":"M","temp":3840,"radius":0,"lum":0,"minhz":0,"maxhz":0,"planets":1,"texture":""}],"satellites":[{"name":"OY Car b","type":"planet","masse":2696.13,"distance":0,"temp":0,"radius":11.63,"semiMajorAxis":924514840.926,"eccentricity":0,"inclination":0,"siderealOrbitPeriod":0,"omega":0,"confirmed":1,"habitable":0,"habitableMoon":0,"esi":"0","method":"Pulsar","year":"2014.00","tempClass":"","class":"jovian","color":null,"texture":"-jovian.jpg"}]}