{"id":1752,"name":"TrES-1b","stars":[{"name":"TrES-1b","type":"star","distance":157,"spec":"K","temp":5150,"radius":0.85,"lum":0.469677,"minhz":0.533,"maxhz":1.281,"planets":1,"texture":""}],"satellites":[{"name":"TrES-1b","type":"planet","masse":241.95,"distance":157,"temp":1063.9,"radius":12.31,"semiMajorAxis":5879196.31851,"eccentricity":0,"inclination":88.4,"siderealOrbitPeriod":3.03,"omega":0,"confirmed":1,"habitable":0,"habitableMoon":0,"esi":"0.08","method":"Transit","year":"2004.00","tempClass":"hot","class":"jovian","color":null,"texture":"hot-jovian.jpg"}]}