{"id":1768,"name":"V391 Peg","stars":[{"name":"V391 Peg","type":"star","distance":1400,"spec":"s","temp":29300,"radius":0.23,"lum":34.979689,"minhz":4.101,"maxhz":9.451,"planets":1,"texture":""}],"satellites":[{"name":"V391 Peg b","type":"planet","masse":1017.41,"distance":1400,"temp":475.2,"radius":11.59,"semiMajorAxis":254316380.19,"eccentricity":0,"inclination":0,"siderealOrbitPeriod":1170,"omega":0,"confirmed":1,"habitable":0,"habitableMoon":0,"esi":"0.17","method":"Pulsar","year":"2007.00","tempClass":"hot","class":"jovian","color":null,"texture":"hot-jovian.jpg"}]}