{"id":1858,"name":"WASP-103","stars":[{"name":"WASP-103","type":"star","distance":470,"spec":"F","temp":6110,"radius":1.44,"lum":2.578479,"minhz":1.181,"maxhz":2.761,"planets":1,"texture":""}],"satellites":[{"name":"WASP-103 b","type":"planet","masse":473.73,"distance":470,"temp":2291.4,"radius":17.11,"semiMajorAxis":2962037.83986,"eccentricity":0,"inclination":86.3,"siderealOrbitPeriod":0.93,"omega":0,"confirmed":1,"habitable":0,"habitableMoon":0,"esi":"0.05","method":"Transit","year":"2014.00","tempClass":"hot","class":"jovian","color":null,"texture":"hot-jovian.jpg"}]}