{"id":1870,"name":"WISE 1711+3500","stars":[{"name":"WISE 1711+3500","type":"star","distance":19,"spec":"T","temp":580,"radius":0.66,"lum":4.3e-5,"minhz":0.005,"maxhz":0.015,"planets":1,"texture":""}],"satellites":[{"name":"WISE 1711+3500 b","type":"planet","masse":4133.22,"distance":19,"temp":5.3,"radius":11.4,"semiMajorAxis":2243968060.5,"eccentricity":0,"inclination":0,"siderealOrbitPeriod":125000,"omega":0,"confirmed":1,"habitable":0,"habitableMoon":0,"esi":"0.06","method":"Imaging","year":"2012.00","tempClass":"cold","class":"jovian","color":null,"texture":"cold-jovian.jpg"}]}